converter_kunnap/__init__.py
converter_kunnap/converter.py
converter_kunnap-0.0.1.dist-info/METADATA
converter_kunnap-0.0.1.dist-info/WHEEL
converter_kunnap-0.0.1.dist-info/licenses/LICENSE
converter_kunnap-0.0.1.dist-info/RECORD
